[
  {
    "source": "reddit",
    "content": "Would love to see more character customization options! Maybe different armor styles that don't affect stats?",
    "sentiment": 0.7,
    "topics": [
      "customization",
      "cosmetics",
      "armor"
    ],
    "author": "reddit_user_1",
    "timestamp": "2025-12-31T06:44:16.662863",
    "engagement": {
      "upvotes": 145,
      "comments": 23
    },
    "category": "feature_request",
    "priority": 0.38707692307692304
  },
  {
    "source": "reddit",
    "content": "The new update is amazing! Really appreciate the F2P model.",
    "sentiment": 0.9,
    "topics": [
      "update",
      "f2p",
      "appreciation"
    ],
    "author": "reddit_user_2",
    "timestamp": "2025-12-31T06:44:16.662866",
    "engagement": {
      "upvotes": 312,
      "comments": 45
    },
    "category": "praise",
    "priority": 0.6261538461538461
  },
  {
    "source": "reddit",
    "content": "Can we get a guild/clan system? Would make the game more social without any pay-to-win elements.",
    "sentiment": 0.5,
    "topics": [
      "social",
      "guild",
      "clan",
      "multiplayer"
    ],
    "author": "reddit_user_3",
    "timestamp": "2025-12-31T06:44:16.662868",
    "engagement": {
      "upvotes": 256,
      "comments": 67
    },
    "category": "feature_request",
    "priority": 0.5963076923076923
  },
  {
    "source": "reddit",
    "content": "The battle pass is fair and purely cosmetic. This is how F2P should be done!",
    "sentiment": 0.8,
    "topics": [
      "battle_pass",
      "cosmetics",
      "f2p"
    ],
    "author": "reddit_user_4",
    "timestamp": "2025-12-31T06:44:16.662870",
    "engagement": {
      "upvotes": 189,
      "comments": 12
    },
    "category": "praise",
    "priority": 0.3861538461538461
  },
  {
    "source": "reddit",
    "content": "Suggestion: Add daily challenges for earning cosmetic currency.",
    "sentiment": 0.6,
    "topics": [
      "daily_challenges",
      "currency",
      "cosmetics"
    ],
    "author": "reddit_user_5",
    "timestamp": "2025-12-31T06:44:16.662872",
    "engagement": {
      "upvotes": 98,
      "comments": 15
    },
    "category": "feature_request",
    "priority": 0.2855384615384615
  },
  {
    "source": "discord",
    "content": "The new seasonal event is so much fun! Love that all rewards are earnable through gameplay.",
    "sentiment": 0.85,
    "topics": [
      "event",
      "seasonal",
      "rewards",
      "gameplay"
    ],
    "author": "discord_user_1",
    "timestamp": "2025-12-31T06:44:16.662949",
    "engagement": {
      "reactions": 45,
      "replies": 8
    },
    "category": "praise",
    "priority": 0.15846153846153846
  },
  {
    "source": "discord",
    "content": "Would be cool to have emote wheel customization. Could be a great cosmetic option!",
    "sentiment": 0.6,
    "topics": [
      "emotes",
      "customization",
      "cosmetics"
    ],
    "author": "discord_user_2",
    "timestamp": "2025-12-31T06:44:16.662951",
    "engagement": {
      "reactions": 78,
      "replies": 15
    },
    "category": "feature_request",
    "priority": 0.2486153846153846
  },
  {
    "source": "discord",
    "content": "The matchmaking feels balanced. Good job on the MMR system!",
    "sentiment": 0.7,
    "topics": [
      "matchmaking",
      "balance",
      "mmr"
    ],
    "author": "discord_user_3",
    "timestamp": "2025-12-31T06:44:16.662956",
    "engagement": {
      "reactions": 34,
      "replies": 5
    },
    "category": "praise",
    "priority": 0.13692307692307693
  },
  {
    "source": "discord",
    "content": "Can we get more profile customization? Banners, borders, titles - all cosmetic stuff that shows progression.",
    "sentiment": 0.5,
    "topics": [
      "profile",
      "customization",
      "cosmetics",
      "progression"
    ],
    "author": "discord_user_4",
    "timestamp": "2025-12-31T06:44:16.662958",
    "engagement": {
      "reactions": 92,
      "replies": 22
    },
    "category": "feature_request",
    "priority": 0.21046153846153845
  },
  {
    "source": "discord",
    "content": "The tutorial was clear and the game respects my time. No forced ads or energy systems. Refreshing!",
    "sentiment": 0.9,
    "topics": [
      "tutorial",
      "respect",
      "f2p",
      "no_ads"
    ],
    "author": "discord_user_5",
    "timestamp": "2025-12-31T06:44:16.662959",
    "engagement": {
      "reactions": 156,
      "replies": 31
    },
    "category": "praise",
    "priority": 0.36461538461538456
  },
  {
    "source": "steam",
    "content": "Excellent F2P game! No pay-to-win mechanics, just cosmetics. Played for 200 hours and never felt the need to spend money.",
    "sentiment": 0.9,
    "topics": [
      "f2p",
      "cosmetics",
      "no_p2w",
      "gameplay"
    ],
    "author": "steam_user_1",
    "timestamp": "2025-12-31T06:44:16.663013",
    "engagement": {
      "helpful": 234,
      "funny": 12
    },
    "category": "review_positive",
    "priority": 0.45538461538461533
  },
  {
    "source": "steam",
    "content": "Great game! Would love to see more weapon skins. Maybe animated ones as premium cosmetics?",
    "sentiment": 0.8,
    "topics": [
      "skins",
      "weapons",
      "cosmetics",
      "premium"
    ],
    "author": "steam_user_2",
    "timestamp": "2025-12-31T06:44:16.663015",
    "engagement": {
      "helpful": 89,
      "funny": 3
    },
    "category": "feature_request",
    "priority": 0.24676923076923074
  },
  {
    "source": "steam",
    "content": "The battle pass is well-designed. Good value and everything is achievable through gameplay.",
    "sentiment": 0.85,
    "topics": [
      "battle_pass",
      "value",
      "gameplay",
      "progression"
    ],
    "author": "steam_user_3",
    "timestamp": "2025-12-31T06:44:16.663017",
    "engagement": {
      "helpful": 156,
      "funny": 5
    },
    "category": "review_positive",
    "priority": 0.32461538461538464
  },
  {
    "source": "steam",
    "content": "Suggestion: Add a replay system and theater mode. Would be great for content creators!",
    "sentiment": 0.6,
    "topics": [
      "replay",
      "theater",
      "content_creation",
      "streaming"
    ],
    "author": "steam_user_4",
    "timestamp": "2025-12-31T06:44:16.663021",
    "engagement": {
      "helpful": 312,
      "funny": 8
    },
    "category": "feature_request",
    "priority": 0.6676923076923077
  },
  {
    "source": "steam",
    "content": "Love the cosmetic shop! Reasonable prices and no FOMO tactics. This is ethical F2P done right.",
    "sentiment": 0.95,
    "topics": [
      "shop",
      "cosmetics",
      "pricing",
      "ethical_f2p"
    ],
    "author": "steam_user_5",
    "timestamp": "2025-12-31T06:44:16.663029",
    "engagement": {
      "helpful": 445,
      "funny": 21
    },
    "category": "review_positive",
    "priority": 0.7938461538461539
  }
]